{
  "name" : "Nguyễn Văn Săng",
  "otype" : "person"
} {
  "name" : "Nguyễn Đình Quân",
  "otype" : "person"
} {
  "name" : "Trần Hưng Đạo",
  "otype" : "person"
} {
  "name" : "Phạm Văn Nghị",
  "otype" : "person"
} {
  "name" : "Đoàn Nguyên Phó",
  "otype" : "person"
} {
  "name" : "Hoàng Đạo Thúy",
  "otype" : "person"
} {
  "name" : "Phạm Phú Thứ",
  "otype" : "person"
} {
  "name" : "Đinh Tiên Hoàng",
  "otype" : "person"
} {
  "name" : "Mai Am",
  "otype" : "person"
} {
  "name" : "Đỗ Ngọc Du",
  "otype" : "person"
} {
  "name" : "Đỗ Xuân Hợp",
  "otype" : "person"
} {
  "name" : "Phạm Tuân",
  "otype" : "person"
} {
  "name" : "Nguyễn Khoái",
  "otype" : "person"
} {
  "name" : "Châu Hạnh",
  "otype" : "person"
} {
  "name" : "Nguyễn Phan Chánh",
  "otype" : "person"
} {
  "name" : "Nguyễn Xuân On",
  "otype" : "person"
} {
  "name" : "Dương Liễu",
  "otype" : "person"
} {
  "name" : "Trần Điền",
  "otype" : "person"
} {
  "name" : "Trần Mai Linh",
  "otype" : "person"
} {
  "name" : "Triệu Hải",
  "otype" : "person"
} {
  "name" : "Nguyễn Văn Cự",
  "otype" : "person"
} {
  "name" : "Đoàn Công Hớn",
  "otype" : "person"
} {
  "name" : "Hoàng Lương",
  "otype" : "person"
} {
  "name" : "Mai Thị Lựu",
  "otype" : "person"
} {
  "name" : "Triệu Thành",
  "otype" : "person"
} {
  "name" : "Nguyễn Thượng Mẫn",
  "otype" : "person"
} {
  "name" : "Châu Hưng",
  "otype" : "person"
} {
  "name" : "Nguyễn Văn Cừ",
  "otype" : "person"
} {
  "name" : "Lý Anh Côn",
  "otype" : "person"
} {
  "name" : "Vũ Hội",
  "otype" : "person"
} {
  "name" : "Trịnh Thị Miềng",
  "otype" : "person"
} {
  "name" : "Nguyễn Văn Giáp",
  "otype" : "person"
} {
  "name" : "Dương Sơn",
  "otype" : "person"
} {
  "name" : "Mai Anh Tuấn",
  "otype" : "person"
} {
  "name" : "Nguyễn Văn Nguyễn",
  "otype" : "person"
} {
  "name" : "Nguyễn Văn Linh",
  "otype" : "person"
} {
  "name" : "Trần Quang Cơ",
  "otype" : "person"
} {
  "name" : "Đào Ngạn",
  "otype" : "person"
} {
  "name" : "Phan Huy Ích",
  "otype" : "person"
} {
  "name" : "Nguyễn Phúc Chu",
  "otype" : "person"
} {
  "name" : "Vũ Công",
  "otype" : "person"
} {
  "name" : "Vũ Đoài",
  "otype" : "person"
} {
  "name" : "Nguyễn Thị Tần",
  "otype" : "person"
} {
  "name" : "Trần Hoành",
  "otype" : "person"
} {
  "name" : "Nguyễn Phước Chu",
  "otype" : "person"
} {
  "name" : "Vũ Xá",
  "otype" : "person"
} {
  "name" : "Vũ Tùng",
  "otype" : "person"
} {
  "name" : "Đinh Củng Viên",
  "otype" : "person"
} {
  "name" : "Lý Thánh Tông",
  "otype" : "person"
} {
  "name" : "Nguyễn Phúc Tần",
  "otype" : "person"
} {
  "name" : "Nguyễn Tất Thành",
  "otype" : "person"
} {
  "name" : "Dương Vân Nga",
  "otype" : "person"
} {
  "name" : "Lê Liễu",
  "otype" : "person"
} {
  "name" : "phan rang-tháp chàm",
  "otype" : "person"
} {
  "name" : "Phạm Văn Hai",
  "otype" : "person"
} {
  "name" : "Dương Phong",
  "otype" : "person"
} {
  "name" : "Trương Phước Thanh",
  "otype" : "person"
} {
  "name" : "Hồ Bốn",
  "otype" : "person"
} {
  "name" : "Trần Văn Mười",
  "otype" : "person"
} {
  "name" : "Lý Chiêu Hoàng",
  "otype" : "person"
} {
  "name" : "Nguyễn Chích",
  "otype" : "person"
} {
  "name" : "Phan Anh",
  "otype" : "person"
} {
  "name" : "Trần Cao Vân",
  "otype" : "person"
} {
  "name" : "Nguyễn Văn Công",
  "otype" : "person"
} {
  "name" : "Lý Thuờng Kiệt",
  "otype" : "person"
} {
  "name" : "Lê Thị Bạch Cát",
  "otype" : "person"
} {
  "name" : "Dương Văn Dương",
  "otype" : "person"
} {
  "name" : "Trần Thái Tông",
  "otype" : "person"
} {
  "name" : "Hồ Văn Tắng",
  "otype" : "person"
} {
  "name" : "Châu Long",
  "otype" : "person"
} {
  "name" : "Đặng Thị Rành",
  "otype" : "person"
} {
  "name" : "Trương Phước Phan",
  "otype" : "person"
} {
  "name" : "Hồ Huấn Nghiệp",
  "otype" : "person"
} {
  "name" : "Bùi Thế Mỹ",
  "otype" : "person"
} {
  "name" : "Trần Quý Kiên",
  "otype" : "person"
} {
  "name" : "Lưu Hữu Phước",
  "otype" : "person"
} {
  "name" : "Nguyễn Đôn Tiết",
  "otype" : "person"
} {
  "name" : "Nguyễn Văn Mai",
  "otype" : "person"
} {
  "name" : "Trần Đại Nghĩa",
  "otype" : "person"
} {
  "name" : "Trần Văn Hoàng",
  "otype" : "person"
} {
  "name" : "Lý Nam Đế",
  "otype" : "person"
} {
  "name" : "Nguyễn Trọng Lội",
  "otype" : "person"
} {
  "name" : "Trần Văn Kỷ",
  "otype" : "person"
} {
  "name" : "Lê Tự Tài",
  "otype" : "person"
} {
  "name" : "Nguyễn Kiệm",
  "otype" : "person"
} {
  "name" : "Nguyễn Đình Chính",
  "otype" : "person"
} {
  "name" : "Nguyễn Văn Bảo",
  "otype" : "person"
} {
  "name" : "Nguyễn Sĩ Cố",
  "otype" : "person"
} {
  "name" : "Nguyễn Văn Lương",
  "otype" : "person"
} {
  "name" : "Mai Hùng",
  "otype" : "person"
} {
  "name" : "Nguyễn Xuyễn",
  "otype" : "person"
} {
  "name" : "Đặng Văn Bi",
  "otype" : "person"
} {
  "name" : "Phan Đức",
  "otype" : "person"
} {
  "name" : "Trương Quyền",
  "otype" : "person"
} {
  "name" : "Phạm Văn Trí",
  "otype" : "person"
} {
  "name" : "Trịnh Như Khuê",
  "otype" : "person"
} {
  "name" : "Lưu Kiền",
  "otype" : "person"
} {
  "name" : "Triệu Trạch",
  "otype" : "person"
} {
  "name" : "Bùi Thị Xuân",
  "otype" : "person"
} {
  "name" : "Lê Đình Lý",
  "otype" : "person"
} {
  "name" : "Trương Gia Mô",
  "otype" : "person"
} {
  "name" : "Đào Cam Mộc",
  "otype" : "person"
} {
  "name" : "Đoàn Kết",
  "otype" : "person"
} {
  "name" : "Hồ Giám",
  "otype" : "person"
} {
  "name" : "Lê Quí Đôn",
  "otype" : "person"
} {
  "name" : "Trần Phú",
  "otype" : "person"
} {
  "name" : "Vũ Lâm",
  "otype" : "person"
} {
  "name" : "Đỗ Nhuận",
  "otype" : "person"
} {
  "name" : "Nguyễn Hữu Trí",
  "otype" : "person"
} {
  "name" : "Trịnh Quang Nghị",
  "otype" : "person"
} {
  "name" : "Nguyễn Cảnh Dị",
  "otype" : "person"
} {
  "name" : "Mai Dị",
  "otype" : "person"
} {
  "name" : "Đỗ Đăng Tuyền",
  "otype" : "person"
} {
  "name" : "phan rang tháp chàm",
  "otype" : "person"
} {
  "name" : "Nguyễn Văn Tiết",
  "otype" : "person"
} {
  "name" : "Lê Văn Hiển",
  "otype" : "person"
} {
  "name" : "Phan Huy Chú",
  "otype" : "person"
} {
  "name" : "Lê Niệm",
  "otype" : "person"
} {
  "name" : "Nguyễn Trung Trực",
  "otype" : "person"
} {
  "name" : "Nguyễn Trung Ngạn",
  "otype" : "person"
} {
  "name" : "Nguyễn Văn Huyên",
  "otype" : "person"
} {
  "name" : "Trần Bình",
  "otype" : "person"
} {
  "name" : "Phan Đạt Đức",
  "otype" : "person"
} {
  "name" : "Mai Đăng Chơn",
  "otype" : "person"
} {
  "name" : "Trần Văn Dư",
  "otype" : "person"
} {
  "name" : "Lê Vĩnh Huy",
  "otype" : "person"
} {
  "name" : "Đinh Hòa",
  "otype" : "person"
} {
  "name" : "Phạm Phú Cường",
  "otype" : "person"
} {
  "name" : "Vũ Chí Hiếu",
  "otype" : "person"
} {
  "name" : "Hoàng Sơn",
  "otype" : "person"
} {
  "name" : "Hoàng Thu Phố",
  "otype" : "person"
} {
  "name" : "Hoàng Hòa",
  "otype" : "person"
} {
  "name" : "Nguyễn Xuân Khoát",
  "otype" : "person"
} {
  "name" : "Đặng Tất",
  "otype" : "person"
} {
  "name" : "Lê Cơ",
  "otype" : "person"
} {
  "name" : "Hoàng Bật Đạt",
  "otype" : "person"
} {
  "name" : "Trương Quốc Dung",
  "otype" : "person"
} {
  "name" : "Đặng Xuân Bảng",
  "otype" : "person"
} {
  "name" : "Mai Đình",
  "otype" : "person"
} {
  "name" : "Triệu Giang",
  "otype" : "person"
} {
  "name" : "Phạm Văn Chèo",
  "otype" : "person"
} {
  "name" : "Trần Kế Xương",
  "otype" : "person"
} {
  "name" : "Đoàn Nguyễn Tuân",
  "otype" : "person"
} {
  "name" : "Lê Thương",
  "otype" : "person"
} {
  "name" : "Đặng Nghiêm",
  "otype" : "person"
} {
  "name" : "Đào Mỹ",
  "otype" : "person"
} {
  "name" : "Lưu Kiếm",
  "otype" : "person"
} {
  "name" : "Vũ Lạc",
  "otype" : "person"
} {
  "name" : "Lê Thị Hồng",
  "otype" : "person"
} {
  "name" : "Hoàng Diệu 1 Cũ",
  "otype" : "person"
} {
  "name" : "Lê Lộ",
  "otype" : "person"
} {
  "name" : "Nguyễn Ngọc Trai",
  "otype" : "person"
} {
  "name" : "Hoàng Đạo",
  "otype" : "person"
} {
  "name" : "Nguyễn Thái Học Nối Dài",
  "otype" : "person"
} {
  "name" : "Hoàng Minh Giám",
  "otype" : "person"
} {
  "name" : "Trần Văn Thành",
  "otype" : "person"
} {
  "name" : "Nguyễn Hiến Lê",
  "otype" : "person"
} {
  "name" : "Lý Hải",
  "otype" : "person"
} {
  "name" : "Phan Huy Thực",
  "otype" : "person"
} {
  "name" : "Nguyễn Thị Duệ",
  "otype" : "person"
} {
  "name" : "Dương Đức Hiền",
  "otype" : "person"
} {
  "name" : "Hoàng Tường",
  "otype" : "person"
} {
  "name" : "Lý Thành",
  "otype" : "person"
} {
  "name" : "Nguyễn Xí",
  "otype" : "person"
} {
  "name" : "Nguyễn Đình Khơi",
  "otype" : "person"
} {
  "name" : "Nguyễn Thượng Hiền",
  "otype" : "person"
} {
  "name" : "Trần Minh Quyền",
  "otype" : "person"
} {
  "name" : "Trần Văn Kiểu",
  "otype" : "person"
} {
  "name" : "Nguyễn Chính",
  "otype" : "person"
} {
  "name" : "Lê Văn Tách",
  "otype" : "person"
} {
  "name" : "Đặng Nhữ Lâm",
  "otype" : "person"
} {
  "name" : "Nguyễn Hữu Cầu",
  "otype" : "person"
} {
  "name" : "Dương Văn An",
  "otype" : "person"
} {
  "name" : "Dương Quảng Hàm",
  "otype" : "person"
} {
  "name" : "Vũ Thư",
  "otype" : "person"
} {
  "name" : "Phạm Nhữ Tăng",
  "otype" : "person"
} {
  "name" : "Lê Văn Phan",
  "otype" : "person"
} {
  "name" : "Lý Nhơn",
  "otype" : "person"
} {
  "name" : "Dương Hà",
  "otype" : "person"
} {
  "name" : "Trần Cảnh",
  "otype" : "person"
} {
  "name" : "Nguyễn Kiểu",
  "otype" : "person"
} {
  "name" : "Đặng Kim Nở",
  "otype" : "person"
} {
  "name" : "Trần Chánh Chiếu",
  "otype" : "person"
} {
  "name" : "Nguyễn Ư Dĩ",
  "otype" : "person"
} {
  "name" : "Nguyễn Khánh Toàn",
  "otype" : "person"
} {
  "name" : "Đặng Thái Thân",
  "otype" : "person"
} {
  "name" : "Hoàng Hóa",
  "otype" : "person"
} {
  "name" : "Nguyễn Huy Thông",
  "otype" : "person"
} {
  "name" : "Lê Thúc Hoạch",
  "otype" : "person"
} {
  "name" : "Hoàng Hoa Thám",
  "otype" : "person"
} {
  "name" : "Hoàng Hải",
  "otype" : "person"
} {
  "name" : "Nguyễn Thị Diệu",
  "otype" : "person"
} {
  "name" : "Nguyễn Kim",
  "otype" : "person"
} {
  "name" : "Châu Thới",
  "otype" : "person"
} {
  "name" : "Lý Văn Phúc",
  "otype" : "person"
} {
  "name" : "Nguyễn Văn Ngọc",
  "otype" : "person"
} {
  "name" : "Phan Thiết",
  "otype" : "person"
} {
  "name" : "Phạm Văn Cội",
  "otype" : "person"
} {
  "name" : "Trần Nhân Tông",
  "otype" : "person"
} {
  "name" : "Đinh Văn Tả",
  "otype" : "person"
} {
  "name" : "Đào Tông Nguyên",
  "otype" : "person"
} {
  "name" : "Châu Sơn",
  "otype" : "person"
} {
  "name" : "Hoàng Xuyên",
  "otype" : "person"
} {
  "name" : "Dương Đình Cúc",
  "otype" : "person"
} {
  "name" : "Trần Văn Chẩm",
  "otype" : "person"
} {
  "name" : "Đỗ Quang Đâu",
  "otype" : "person"
} {
  "name" : "Hoàng Minh Giam",
  "otype" : "person"
} {
  "name" : "Châu Tiến",
  "otype" : "person"
} {
  "name" : "Nguyễn Thị Định",
  "otype" : "person"
} {
  "name" : "Bùi Hữu Nghĩa",
  "otype" : "person"
} {
  "name" : "Hoàng Hưng",
  "otype" : "person"
} {
  "name" : "Lê Ngô Cát",
  "otype" : "person"
} {
  "name" : "Bùi Xuân Phái",
  "otype" : "person"
} {
  "name" : "Trịnh Lỗi",
  "otype" : "person"
} {
  "name" : "Nguyễn Đại Năng",
  "otype" : "person"
} {
  "name" : "Lý Quốc Bảo",
  "otype" : "person"
} {
  "name" : "Nguyễn Hữu Dật",
  "otype" : "person"
} {
  "name" : "Lê Hồ",
  "otype" : "person"
} {
  "name" : "Phạm Minh Đức",
  "otype" : "person"
} {
  "name" : "Phạm Hồng Thái",
  "otype" : "person"
} {
  "name" : "Trương Văn Quân",
  "otype" : "person"
} {
  "name" : "Nguyễn Văn Sáng",
  "otype" : "person"
} {
  "name" : "Đoàn Xá",
  "otype" : "person"
} {
  "name" : "Trần Điện",
  "otype" : "person"
} {
  "name" : "Lê Chí Dân",
  "otype" : "person"
} {
  "name" : "Dương Vương",
  "otype" : "person"
} {
  "name" : "Vũ Huy Tuấn",
  "otype" : "person"
} {
  "name" : "Phan Rí Thành",
  "otype" : "person"
} {
  "name" : "Trần Thánh Tông",
  "otype" : "person"
} {
  "name" : "Hoàng Trĩ",
  "otype" : "person"
} {
  "name" : "Trần Thanh Mại",
  "otype" : "person"
} {
  "name" : "Châu Thượng Văn",
  "otype" : "person"
} {
  "name" : "Lê Văn Chí",
  "otype" : "person"
} {
  "name" : "Nguyễn Thị Diệu Hương",
  "otype" : "person"
} {
  "name" : "Nguyễn Văn Kim",
  "otype" : "person"
} {
  "name" : "Mai Tùng",
  "otype" : "person"
} {
  "name" : "Mai Văn Vĩnh",
  "otype" : "person"
} {
  "name" : "Trần Nhân Trung",
  "otype" : "person"
} {
  "name" : "Hoàng Lê Kha",
  "otype" : "person"
} {
  "name" : "Phạm Vấn",
  "otype" : "person"
} {
  "name" : "Triệu Đà",
  "otype" : "person"
} {
  "name" : "Nguyễn Khắc Cần",
  "otype" : "person"
} {
  "name" : "Nguyễn Triệu Luật",
  "otype" : "person"
} {
  "name" : "Phan Dũng",
  "otype" : "person"
} {
  "name" : "Nguyễn Ngọc Vũ",
  "otype" : "person"
} {
  "name" : "Nguyễn Khuyến",
  "otype" : "person"
} {
  "name" : "Phan Tôn",
  "otype" : "person"
} {
  "name" : "Hồ Đắc Kiện",
  "otype" : "person"
} {
  "name" : "Triệu Chính",
  "otype" : "person"
} {
  "name" : "Phan Thành Tài",
  "otype" : "person"
} {
  "name" : "Châu Thắng",
  "otype" : "person"
} {
  "name" : "Châu Thôn",
  "otype" : "person"
} {
  "name" : "Nguyễn Chế Nghĩa",
  "otype" : "person"
} {
  "name" : "Mai Thủy",
  "otype" : "person"
} {
  "name" : "Trần Kê Xương",
  "otype" : "person"
} {
  "name" : "Lê Văn Thọ",
  "otype" : "person"
} {
  "name" : "Nguyễn Viết Xuân",
  "otype" : "person"
} {
  "name" : "Nguyễn Khiêm",
  "otype" : "person"
} {
  "name" : "Đào Cử",
  "otype" : "person"
} {
  "name" : "Lưu Phương",
  "otype" : "person"
} {
  "name" : "Trần Hưng Đạo B",
  "otype" : "person"
} {
  "name" : "Nguyễn Ngọc Nhựt",
  "otype" : "person"
} {
  "name" : "Châu Thành",
  "otype" : "person"
} {
  "name" : "Trương Hán Siêu",
  "otype" : "person"
} {
  "name" : "Hoàng Dư Khương",
  "otype" : "person"
} {
  "name" : "Phan Đình Thông",
  "otype" : "person"
} {
  "name" : "Đặng Minh Trứ",
  "otype" : "person"
} {
  "name" : "Trần Thúc Nhẫn",
  "otype" : "person"
} {
  "name" : "Lê Văn Thịnh",
  "otype" : "person"
} {
  "name" : "Phạm Quý Thích",
  "otype" : "person"
} {
  "name" : "Phạm Đình Hổ",
  "otype" : "person"
} {
  "name" : "Đinh Long",
  "otype" : "person"
} {
  "name" : "Trần Ngọc Lên",
  "otype" : "person"
} {
  "name" : "Phạm Đình Hồ",
  "otype" : "person"
} {
  "name" : "Phan Liêm",
  "otype" : "person"
} {
  "name" : "Vũ Đông",
  "otype" : "person"
} {
  "name" : "Triệu Quang Phục",
  "otype" : "person"
} {
  "name" : "Châu Quế Hạ",
  "otype" : "person"
} {
  "name" : "Đinh Trang Thư Ợng",
  "otype" : "person"
} {
  "name" : "Lê Thị Riêng",
  "otype" : "person"
} {
  "name" : "Hồ Văn Hiển",
  "otype" : "person"
} {
  "name" : "Trương Công Định",
  "otype" : "person"
} {
  "name" : "Lê Thanh Nghị",
  "otype" : "person"
} {
  "name" : "Hoàng Văn Thái",
  "otype" : "person"
} {
  "name" : "Đào Tấn",
  "otype" : "person"
} {
  "name" : "Lê Độ",
  "otype" : "person"
} {
  "name" : "Trần Nguyên Hãn",
  "otype" : "person"
} {
  "name" : "Lê Văn Thứ",
  "otype" : "person"
} {
  "name" : "Đặng Nguyên Cẩn",
  "otype" : "person"
} {
  "name" : "Nguyễn Sơn Hà",
  "otype" : "person"
} {
  "name" : "Phạm Nổi",
  "otype" : "person"
} {
  "name" : "Trần Văn Đang",
  "otype" : "person"
} {
  "name" : "Triệu Hòa",
  "otype" : "person"
} {
  "name" : "Trần Hòa",
  "otype" : "person"
} {
  "name" : "Nguyễn Bá Tòng",
  "otype" : "person"
} {
  "name" : "Lê Cảnh Tuân",
  "otype" : "person"
} {
  "name" : "Nguyễn Thị Minh Khai",
  "otype" : "person"
} {
  "name" : "Trương Minh Ký",
  "otype" : "person"
} {
  "name" : "Nguyễn Khang",
  "otype" : "person"
} {
  "name" : "Nguyễn Thi",
  "otype" : "person"
} {
  "name" : "Lê Lăng",
  "otype" : "person"
} {
  "name" : "Hoàng Đạo Thành",
  "otype" : "person"
} {
  "name" : "Nguyễn Thái Sơn",
  "otype" : "person"
} {
  "name" : "Hoàng Ngân",
  "otype" : "person"
} {
  "name" : "Triệu Phước",
  "otype" : "person"
} {
  "name" : "Vũ Chính",
  "otype" : "person"
} {
  "name" : "Trần Lãm",
  "otype" : "person"
} {
  "name" : "Phan Rí Cửa",
  "otype" : "person"
} {
  "name" : "Lê Quang Định",
  "otype" : "person"
} {
  "name" : "Lê Hoàng Thái",
  "otype" : "person"
} {
  "name" : "Phạm Thận Duật",
  "otype" : "person"
} {
  "name" : "Phạm Văn Đới",
  "otype" : "person"
} {
  "name" : "Dương Tử Giang",
  "otype" : "person"
} {
  "name" : "Đỗ Lợi",
  "otype" : "person"
} {
  "name" : "Đào Xá",
  "otype" : "person"
} {
  "name" : "Đoàn Lập",
  "otype" : "person"
} {
  "name" : "Trần Huy Diệu",
  "otype" : "person"
} {
  "name" : "Đặng Lộ",
  "otype" : "person"
} {
  "name" : "Mai Hóa",
  "otype" : "person"
} {
  "name" : "Phạm Văn Chiêu",
  "otype" : "person"
} {
  "name" : "Đỗ Hưng Viễn",
  "otype" : "person"
} {
  "name" : "Hồ Biểu Chánh",
  "otype" : "person"
} {
  "name" : "Bùi Tú Toàn",
  "otype" : "person"
} {
  "name" : "Nguyễn Thị Huỳnh",
  "otype" : "person"
} {
  "name" : "Lưu Văn Lang",
  "otype" : "person"
} {
  "name" : "Đặng Hữu Phổ",
  "otype" : "person"
} {
  "name" : "Đỗ Sơn",
  "otype" : "person"
} {
  "name" : "Bùi Lâm",
  "otype" : "person"
} {
  "name" : "Trần Hoàng Na",
  "otype" : "person"
} {
  "name" : "Lê Duẩn",
  "otype" : "person"
} {
  "name" : "Nguyễn Thị Sóc",
  "otype" : "person"
} {
  "name" : "Trần Quang Diệu",
  "otype" : "person"
} {
  "name" : "Hoàng Khai",
  "otype" : "person"
} {
  "name" : "Nguyễn Văn Khạ",
  "otype" : "person"
} {
  "name" : "Trần Văn Thời",
  "otype" : "person"
} {
  "name" : "Hồ Hảo Hớn",
  "otype" : "person"
} {
  "name" : "Phan Ngữ",
  "otype" : "person"
} {
  "name" : "Vũ Hữu Lợi",
  "otype" : "person"
} {
  "name" : "Phan Văn Sửu",
  "otype" : "person"
} {
  "name" : "Hoàng Nông",
  "otype" : "person"
} {
  "name" : "Nguyễn Thiện Thuật",
  "otype" : "person"
} {
  "name" : "Bùi Bằng Đoàn",
  "otype" : "person"
} {
  "name" : "Lê Ninh",
  "otype" : "person"
} {
  "name" : "Lê Đình Chinh",
  "otype" : "person"
} {
  "name" : "Nguyễn Văn Đượm",
  "otype" : "person"
} {
  "name" : "Phan Đình Giót",
  "otype" : "person"
} {
  "name" : "Phan Văn Khỏe",
  "otype" : "person"
} {
  "name" : "Hồ Bắc Di",
  "otype" : "person"
} {
  "name" : "Đào Sư Tích",
  "otype" : "person"
} {
  "name" : "Nguyễn Xiển",
  "otype" : "person"
} {
  "name" : "Trần Lê",
  "otype" : "person"
} {
  "name" : "Phan Thúc Duyện",
  "otype" : "person"
} {
  "name" : "Nguyễn Mỹ Ca",
  "otype" : "person"
} {
  "name" : "Triệu Phong",
  "otype" : "person"
} {
  "name" : "Nguyễn Thị Nghĩa",
  "otype" : "person"
} {
  "name" : "Phan Phúc Duyệt",
  "otype" : "person"
} {
  "name" : "Bùi Huy Bích",
  "otype" : "person"
} {
  "name" : "Nguyễn Văn Quỳ",
  "otype" : "person"
} {
  "name" : "Trần Văn Trà",
  "otype" : "person"
} {
  "name" : "Nguyễn Văn Vỹ",
  "otype" : "person"
} {
  "name" : "Trần Tân",
  "otype" : "person"
} {
  "name" : "Hoàng Long",
  "otype" : "person"
} {
  "name" : "Hồ Ngọc Cẩn",
  "otype" : "person"
} {
  "name" : "Nguyễn Văn Thủ",
  "otype" : "person"
} {
  "name" : "Lê Duẫn",
  "otype" : "person"
} {
  "name" : "Phan Văn Đối",
  "otype" : "person"
} {
  "name" : "Mai Văn Ngọc",
  "otype" : "person"
} {
  "name" : "Mai Hắc Đế",
  "otype" : "person"
} {
  "name" : "Đinh Nhu",
  "otype" : "person"
} {
  "name" : "Nguyễn Đăng Giai",
  "otype" : "person"
} {
  "name" : "Châu Lăng",
  "otype" : "person"
} {
  "name" : "Nguyễn Khiết",
  "otype" : "person"
} {
  "name" : "Trần Quý Cáp",
  "otype" : "person"
} {
  "name" : "Trương Lương",
  "otype" : "person"
} {
  "name" : "Nguyễn Huân",
  "otype" : "person"
} {
  "name" : "Trần Văn Thới",
  "otype" : "person"
} {
  "name" : "Nguyễn Thị Rành",
  "otype" : "person"
} {
  "name" : "Nguyễn Lương Bằng",
  "otype" : "person"
} {
  "name" : "Nguyễn Đức Tịnh",
  "otype" : "person"
} {
  "name" : "Bùi Ngọc Thu",
  "otype" : "person"
} {
  "name" : "Phan Tấn Mười",
  "otype" : "person"
} {
  "name" : "Châu Hoàn",
  "otype" : "person"
} {
  "name" : "Lê Mao",
  "otype" : "person"
} {
  "name" : "Vũ Nông",
  "otype" : "person"
} {
  "name" : "Lê Minh Nhựt",
  "otype" : "person"
} {
  "name" : "Trần Quốc Hoàn",
  "otype" : "person"
} {
  "name" : "Vũ Ngọc Phan",
  "otype" : "person"
} {
  "name" : "Trần Tướng Công",
  "otype" : "person"
} {
  "name" : "Nguyễn Văn Năm",
  "otype" : "person"
} {
  "name" : "Hoàng Cầu",
  "otype" : "person"
} {
  "name" : "Vũ Thạnh",
  "otype" : "person"
} {
  "name" : "Phạm Ngọc Thạch",
  "otype" : "person"
} {
  "name" : "Trần Trung Lập",
  "otype" : "person"
} {
  "name" : "Dương Hưu",
  "otype" : "person"
} {
  "name" : "Nguyễn Thức Tự",
  "otype" : "person"
} {
  "name" : "Phan Rang Tháp Chàm",
  "otype" : "person"
} {
  "name" : "Phạm Đình Toái",
  "otype" : "person"
} {
  "name" : "Lê Hùng Yên",
  "otype" : "person"
} {
  "name" : "Lê Thành Phương",
  "otype" : "person"
} {
  "name" : "Hoàng Xuân Hãn",
  "otype" : "person"
} {
  "name" : "Đặng Dung",
  "otype" : "person"
} {
  "name" : "Vũ Di",
  "otype" : "person"
} {
  "name" : "Đỗ Văn Dậy",
  "otype" : "person"
} {
  "name" : "Trần Thị Ngần",
  "otype" : "person"
} {
  "name" : "phan rang- tháp chàm",
  "otype" : "person"
} {
  "name" : "Phan Văn Bảy",
  "otype" : "person"
} {
  "name" : "Lê Chân",
  "otype" : "person"
} {
  "name" : "Lê Văn Hưu",
  "otype" : "person"
} {
  "name" : "Phan Thế Hiển",
  "otype" : "person"
} {
  "name" : "Lý Quốc",
  "otype" : "person"
} {
  "name" : "Nguyễn Thị Nê",
  "otype" : "person"
} {
  "name" : "Đào Viên",
  "otype" : "person"
} {
  "name" : "Lê Châu",
  "otype" : "person"
} {
  "name" : "Lê Minh Sơn",
  "otype" : "person"
} {
  "name" : "Lê Gia Định",
  "otype" : "person"
} {
  "name" : "Lý Phục Man",
  "otype" : "person"
} {
  "name" : "Hoàng Quế",
  "otype" : "person"
} {
  "name" : "Lê Văn Khương",
  "otype" : "person"
} {
  "name" : "Nguyễn Tuân",
  "otype" : "person"
} {
  "name" : "Trần Hợi",
  "otype" : "person"
} {
  "name" : "Nguyễn Tam Trinh",
  "otype" : "person"
} {
  "name" : "Nguyễn Văn Lịch",
  "otype" : "person"
} {
  "name" : "Đinh Công Tráng",
  "otype" : "person"
} {
  "name" : "Trần Cao",
  "otype" : "person"
} {
  "name" : "Nguyễn Văn Hưởng",
  "otype" : "person"
} {
  "name" : "Nguyễn Hữu Hào",
  "otype" : "person"
} {
  "name" : "Hoàng Sâm",
  "otype" : "person"
} {
  "name" : "Nguyễn Văn Đừng",
  "otype" : "person"
} {
  "name" : "Nguyễn Phúc Thái",
  "otype" : "person"
} {
  "name" : "Trần Triệu Luật",
  "otype" : "person"
} {
  "name" : "Trương Vĩnh Ký",
  "otype" : "person"
} {
  "name" : "Lê Thị Siêng",
  "otype" : "person"
} {
  "name" : "Châu Hưng A",
  "otype" : "person"
} {
  "name" : "Trần Văn Ơn",
  "otype" : "person"
} {
  "name" : "Lê Trọng Tấn",
  "otype" : "person"
} {
  "name" : "Đào Thịnh",
  "otype" : "person"
} {
  "name" : "Vũ Hữu",
  "otype" : "person"
} {
  "name" : "Triệu An",
  "otype" : "person"
} {
  "name" : "Châu Khánh",
  "otype" : "person"
} {
  "name" : "Hoàng Hữu Nam",
  "otype" : "person"
} {
  "name" : "hoàng quốc việt",
  "otype" : "person"
} {
  "name" : "Hoàng Su Phì",
  "otype" : "person"
} {
  "name" : "Nguyễn Đức Thuận",
  "otype" : "person"
} {
  "name" : "Phạm Kha",
  "otype" : "person"
} {
  "name" : "Nguyễn Thị Thập",
  "otype" : "person"
} {
  "name" : "Đoàn Thị Điểm",
  "otype" : "person"
} {
  "name" : "Trần Hữu Trang",
  "otype" : "person"
} {
  "name" : "Đinh Đức Thiện",
  "otype" : "person"
} {
  "name" : "Đinh Liên",
  "otype" : "person"
} {
  "name" : "Trương Hoàng Thành",
  "otype" : "person"
} {
  "name" : "Lê Đức Thọ",
  "otype" : "person"
} {
  "name" : "Nguyễn Nghiêm",
  "otype" : "person"
} {
  "name" : "Mai An Tiêm",
  "otype" : "person"
} {
  "name" : "Phạm Văn Hân",
  "otype" : "person"
} {
  "name" : "Đỗ Ngọc Thạnh",
  "otype" : "person"
} {
  "name" : "Nguyễn Súy",
  "otype" : "person"
} {
  "name" : "Nguyễn Huy Điển",
  "otype" : "person"
} {
  "name" : "Đoàn Như Hài",
  "otype" : "person"
} {
  "name" : "Trần Văn Kiều",
  "otype" : "person"
} {
  "name" : "Hoàng Kế Viêm",
  "otype" : "person"
} {
  "name" : "Đặng Lễ",
  "otype" : "person"
} {
  "name" : "Nguyễn Gia Thiều",
  "otype" : "person"
} {
  "name" : "Vũ Thắng",
  "otype" : "person"
} {
  "name" : "Phan Văn Trương",
  "otype" : "person"
} {
  "name" : "Hoàng Đạo Thuý",
  "otype" : "person"
} {
  "name" : "Lưu Nhân Chú",
  "otype" : "person"
} {
  "name" : "Đặng Thai Mai",
  "otype" : "person"
} {
  "name" : "Hoàng An",
  "otype" : "person"
} {
  "name" : "Vũ Quý",
  "otype" : "person"
} {
  "name" : "Dương Huy",
  "otype" : "person"
} {
  "name" : "Trần Văn Nữa",
  "otype" : "person"
} {
  "name" : "Trần Bá Giao",
  "otype" : "person"
} {
  "name" : "Hoàng Văn Lịch",
  "otype" : "person"
} {
  "name" : "Trịnh Văn Cấn",
  "otype" : "person"
} {
  "name" : "Lê Ngân",
  "otype" : "person"
} {
  "name" : "Trương Mỹ",
  "otype" : "person"
} {
  "name" : "Nguyễn Bá Học",
  "otype" : "person"
} {
  "name" : "Lê Quang Kim",
  "otype" : "person"
} {
  "name" : "Trần Tiến Đông",
  "otype" : "person"
} {
  "name" : "Phan Văn Huân",
  "otype" : "person"
} {
  "name" : "Trịnh Hoài Đức",
  "otype" : "person"
} {
  "name" : "Phạm Sư Mạnh",
  "otype" : "person"
} {
  "name" : "Phan Văn Lâu",
  "otype" : "person"
} {
  "name" : "Dương Thưởng",
  "otype" : "person"
} {
  "name" : "Lê Thánh Tôn",
  "otype" : "person"
} {
  "name" : "Hoàng Lâu",
  "otype" : "person"
} {
  "name" : "Vũ Sơn",
  "otype" : "person"
} {
  "name" : "Vũ An",
  "otype" : "person"
} {
  "name" : "Phan Thanh",
  "otype" : "person"
} {
  "name" : "Triệu Sơn",
  "otype" : "person"
} {
  "name" : "Nguyễn Tử Nha",
  "otype" : "person"
} {
  "name" : "Đỗ Xuyên",
  "otype" : "person"
} {
  "name" : "Dương Tơ",
  "otype" : "person"
} {
  "name" : "Hồ Hoàn Kiếm",
  "otype" : "person"
} {
  "name" : "Phạm Thái Bường",
  "otype" : "person"
} {
  "name" : "Triệu Đông",
  "otype" : "person"
} {
  "name" : "Nguyễn Phích",
  "otype" : "person"
} {
  "name" : "Nguyễn Thị Rư",
  "otype" : "person"
} {
  "name" : "Lý Trạch",
  "otype" : "person"
} {
  "name" : "Nguyễn Thần Hiến",
  "otype" : "person"
} {
  "name" : "Mai Xuân Thưởng",
  "otype" : "person"
} {
  "name" : "Nguyễn Hoàng Tôn",
  "otype" : "person"
} {
  "name" : "Hồ Xuân Hương",
  "otype" : "person"
} {
  "name" : "Hoàng Giang",
  "otype" : "person"
} {
  "name" : "Hoàng Tăng Bí",
  "otype" : "person"
} {
  "name" : "Phạm Đôn",
  "otype" : "person"
} {
  "name" : "Trần Mai Ninh",
  "otype" : "person"
} {
  "name" : "Đặng Công Bỉnh",
  "otype" : "person"
} {
  "name" : "Hoàng Văn Hợp",
  "otype" : "person"
} {
  "name" : "Nguyễn Bá Huân",
  "otype" : "person"
} {
  "name" : "Nguyễn Văn Mại",
  "otype" : "person"
} {
  "name" : "Nguyễn Văn Vĩnh",
  "otype" : "person"
} {
  "name" : "Mai Sao",
  "otype" : "person"
} {
  "name" : "Trần Nhật Duật",
  "otype" : "person"
} {
  "name" : "Châu Thái",
  "otype" : "person"
} {
  "name" : "Trần Anh Tông",
  "otype" : "person"
} {
  "name" : "Dương Đình Hội",
  "otype" : "person"
} {
  "name" : "Nguyễn Văn Thảnh",
  "otype" : "person"
} {
  "name" : "Trương Mít",
  "otype" : "person"
} {
  "name" : "Phạm Như Xương",
  "otype" : "person"
} {
  "name" : "Nguyễn Như Đổ",
  "otype" : "person"
} {
  "name" : "Phạm Thị Liên",
  "otype" : "person"
} {
  "name" : "Trần Tống",
  "otype" : "person"
} {
  "name" : "Phạm Hữu Điều",
  "otype" : "person"
} {
  "name" : "Phan Kế Bính",
  "otype" : "person"
} {
  "name" : "Hồ Văn Tư",
  "otype" : "person"
} {
  "name" : "Nguyễn Phúc Lan",
  "otype" : "person"
} {
  "name" : "Mai Lạp",
  "otype" : "person"
} {
  "name" : "Trương Mai",
  "otype" : "person"
} {
  "name" : "Nguyễn Siêu",
  "otype" : "person"
} {
  "name" : "Nguyễn Văn Nghi",
  "otype" : "person"
} {
  "name" : "Mai Phúc",
  "otype" : "person"
} {
  "name" : "Trần Thiện Chánh",
  "otype" : "person"
} {
  "name" : "Châu Giang",
  "otype" : "person"
} {
  "name" : "Mai Hạ",
  "otype" : "person"
} {
  "name" : "Nguyễn Phúc Lai",
  "otype" : "person"
} {
  "name" : "Dương Xá",
  "otype" : "person"
} {
  "name" : "Bùi Hửu Nghĩa",
  "otype" : "person"
} {
  "name" : "Mai Long",
  "otype" : "person"
} {
  "name" : "Nguyễn Trường Tộ",
  "otype" : "person"
} {
  "name" : "Vũ Trung",
  "otype" : "person"
} {
  "name" : "Trịnh Tường",
  "otype" : "person"
} {
  "name" : "Trần Hái Phụng",
  "otype" : "person"
} {
  "name" : "Nguyễn Quý Yêm",
  "otype" : "person"
} {
  "name" : "Châu Minh",
  "otype" : "person"
} {
  "name" : "Dương Quỳ",
  "otype" : "person"
} {
  "name" : "Châu Đức",
  "otype" : "person"
} {
  "name" : "Đỗ Thị Tâm",
  "otype" : "person"
} {
  "name" : "Bùi Văn Ba",
  "otype" : "person"
} {
  "name" : "Đoàn Thượng",
  "otype" : "person"
} {
  "name" : "Lý Thường Kiệt",
  "otype" : "person"
} {
  "name" : "Nguyễn Hiền",
  "otype" : "person"
} {
  "name" : "Nguyễn Chi Phương",
  "otype" : "person"
} {
  "name" : "Lưu Sơn",
  "otype" : "person"
} {
  "name" : "Lưu Ngọc",
  "otype" : "person"
} {
  "name" : "Nguyễn Đức Cảnh",
  "otype" : "person"
} {
  "name" : "Phan Tứ",
  "otype" : "person"
} {
  "name" : "Trần Văn Giáp",
  "otype" : "person"
} {
  "name" : "Trương Văn Hải",
  "otype" : "person"
} {
  "name" : "Phạm Mệnh",
  "otype" : "person"
} {
  "name" : "Phan Văn Hớn",
  "otype" : "person"
} {
  "name" : "Lê Đình Chi",
  "otype" : "person"
} {
  "name" : "Vũ Bản",
  "otype" : "person"
} {
  "name" : "Trịnh Thị Nghỉ",
  "otype" : "person"
} {
  "name" : "Đinh Tường",
  "otype" : "person"
} {
  "name" : "Hoàng Trinh",
  "otype" : "person"
} {
  "name" : "Nguyễn Cừ Đàm",
  "otype" : "person"
} {
  "name" : "phan thiết",
  "otype" : "person"
} {
  "name" : "Phan Lâm",
  "otype" : "person"
} {
  "name" : "Bùi Thị Cúc",
  "otype" : "person"
} {
  "name" : "Vũ Huy Tấn",
  "otype" : "person"
} {
  "name" : "Trần Đăng Ninh",
  "otype" : "person"
} {
  "name" : "Châu Phú An",
  "otype" : "person"
} {
  "name" : "Trần Hải Phụng",
  "otype" : "person"
} {
  "name" : "Trần Khát Chân",
  "otype" : "person"
} {
  "name" : "Lê Hữu Trác",
  "otype" : "person"
} {
  "name" : "Phạm Nhữ Tân",
  "otype" : "person"
} {
  "name" : "Phạm Mạnh Chiêu",
  "otype" : "person"
} {
  "name" : "Nguyễn Nhạc",
  "otype" : "person"
} {
  "name" : "Nguyễn Duy Trinh",
  "otype" : "person"
} {
  "name" : "Nguyễn Thế Lộc",
  "otype" : "person"
} {
  "name" : "Hoàng Minh Đạo",
  "otype" : "person"
} {
  "name" : "Hoàng Văn Thụ",
  "otype" : "person"
} {
  "name" : "Nguyễn Thị Tú",
  "otype" : "person"
} {
  "name" : "Mai Trung",
  "otype" : "person"
} {
  "name" : "Nguyễn Lâm",
  "otype" : "person"
} {
  "name" : "Châu Thành A",
  "otype" : "person"
} {
  "name" : "Nguyễn Thông",
  "otype" : "person"
} {
  "name" : "Dương Đình Nghệ",
  "otype" : "person"
} {
  "name" : "Lê Minh Xuân",
  "otype" : "person"
} {
  "name" : "Bùi Ngọc Dương",
  "otype" : "person"
} {
  "name" : "Nguyễn Bính",
  "otype" : "person"
} {
  "name" : "Dương Hòa",
  "otype" : "person"
} {
  "name" : "Nguyễn Cừu Đàm",
  "otype" : "person"
} {
  "name" : "Hồ Học Lãm",
  "otype" : "person"
} {
  "name" : "Đỗ Năng Tế",
  "otype" : "person"
} {
  "name" : "Lê Thị Hoa",
  "otype" : "person"
} {
  "name" : "Trần Thị Lý",
  "otype" : "person"
} {
  "name" : "Bùi Đình Tuý",
  "otype" : "person"
} {
  "name" : "Đỗ Thừa Luông",
  "otype" : "person"
} {
  "name" : "Nguyễn Quý Đức",
  "otype" : "person"
} {
  "name" : "Lý Quốc Sư",
  "otype" : "person"
} {
  "name" : "Lê Đại Hành",
  "otype" : "person"
} {
  "name" : "Lê Đình Thám",
  "otype" : "person"
} {
  "name" : "Trần Thời",
  "otype" : "person"
} {
  "name" : "Châu Văn Liêm",
  "otype" : "person"
} {
  "name" : "Nguyễn Văn Tố",
  "otype" : "person"
} {
  "name" : "Hồ Văn Cống",
  "otype" : "person"
} {
  "name" : "Châu Phong",
  "otype" : "person"
} {
  "name" : "Nguyễn Thời Trung",
  "otype" : "person"
} {
  "name" : "Nguyễn Văn Hỗn",
  "otype" : "person"
} {
  "name" : "Lê Duy Nhuận",
  "otype" : "person"
} {
  "name" : "Lê Trung Đình",
  "otype" : "person"
} {
  "name" : "Phan Rang Tháp Tràm",
  "otype" : "person"
} {
  "name" : "Phan Văn Duật",
  "otype" : "person"
} {
  "name" : "Đào Trí",
  "otype" : "person"
} {
  "name" : "Lê Thánh Tông",
  "otype" : "person"
} {
  "name" : "Nguyễn Phan Vinh",
  "otype" : "person"
} {
  "name" : "Triệu Đại",
  "otype" : "person"
} {
  "name" : "Phạm Viết Chính",
  "otype" : "person"
} {
  "name" : "Phan Tây Hồ",
  "otype" : "person"
} {
  "name" : "Nguyễn Văn Hiền",
  "otype" : "person"
} {
  "name" : "Nguyễn Văn Thoại",
  "otype" : "person"
} {
  "name" : "Nguyễn Quyền",
  "otype" : "person"
} {
  "name" : "Nguyễn Bặc",
  "otype" : "person"
} {
  "name" : "Đinh Kim Lưu",
  "otype" : "person"
} {
  "name" : "Hoàng Văn Hòe",
  "otype" : "person"
} {
  "name" : "Trần Văn Côi",
  "otype" : "person"
} {
  "name" : "Dương Kinh",
  "otype" : "person"
} {
  "name" : "Hoàng Thiều Hoa",
  "otype" : "person"
} {
  "name" : "Đặng Chất",
  "otype" : "person"
} {
  "name" : "Bùi Tư Toàn",
  "otype" : "person"
} {
  "name" : "Bùi Chu",
  "otype" : "person"
} {
  "name" : "Đinh Đàm",
  "otype" : "person"
} {
  "name" : "Trần Duy Hưng",
  "otype" : "person"
} {
  "name" : "Mai Khôi",
  "otype" : "person"
} {
  "name" : "Lê Chánh",
  "otype" : "person"
} {
  "name" : "Phạm Bành",
  "otype" : "person"
} {
  "name" : "Châu Lý",
  "otype" : "person"
} {
  "name" : "Lý Tuệ",
  "otype" : "person"
} {
  "name" : "Nguyễn Bá Tuyền",
  "otype" : "person"
} {
  "name" : "Lý Vĩnh",
  "otype" : "person"
} {
  "name" : "Mai Sơn",
  "otype" : "person"
} {
  "name" : "Lê Thị Trung",
  "otype" : "person"
} {
  "name" : "Hoàng Vân",
  "otype" : "person"
} {
  "name" : "Hoàng Tiến",
  "otype" : "person"
} {
  "name" : "Hoàng Thanh",
  "otype" : "person"
} {
  "name" : "Nguyễn Khắc Hiếu",
  "otype" : "person"
} {
  "name" : "Bùi Quốc Khánh",
  "otype" : "person"
} {
  "name" : "Mai Châu",
  "otype" : "person"
} {
  "name" : "Lê Văn Ninh",
  "otype" : "person"
} {
  "name" : "Phan Hòa",
  "otype" : "person"
} {
  "name" : "Phan Tiến",
  "otype" : "person"
} {
  "name" : "Nguyễn Huy Lượng",
  "otype" : "person"
} {
  "name" : "Nguyễn Văn Chiêm",
  "otype" : "person"
} {
  "name" : "Triệu Lăng",
  "otype" : "person"
} {
  "name" : "Lê Bá Trinh",
  "otype" : "person"
} {
  "name" : "Triệu Dân",
  "otype" : "person"
} {
  "name" : "Vũ Lễ",
  "otype" : "person"
} {
  "name" : "Đặng Thị Nhu",
  "otype" : "person"
} {
  "name" : "Đào Duy Từ",
  "otype" : "person"
} {
  "name" : "Bùi Xá",
  "otype" : "person"
} {
  "name" : "phan đình giót",
  "otype" : "person"
} {
  "name" : "Dương Văn Cam",
  "otype" : "person"
} {
  "name" : "Nguyễn Hữu Huân",
  "otype" : "person"
} {
  "name" : "Lê Văn Cuội",
  "otype" : "person"
} {
  "name" : "Lý Chính Thắng",
  "otype" : "person"
} {
  "name" : "Phan Thanh Giản",
  "otype" : "person"
} {
  "name" : "Trương Văn Thành",
  "otype" : "person"
} {
  "name" : "Vũ Tây",
  "otype" : "person"
} {
  "name" : "Vũ Lăng",
  "otype" : "person"
} {
  "name" : "Mai Phụ",
  "otype" : "person"
} {
  "name" : "Lý Văn Lâm",
  "otype" : "person"
} {
  "name" : "Triệu Nguyên",
  "otype" : "person"
} {
  "name" : "Lưu Hoàng",
  "otype" : "person"
} {
  "name" : "Nguyễn Ngọc Lộc",
  "otype" : "person"
} {
  "name" : "Trương Đình Hợi",
  "otype" : "person"
} {
  "name" : "Đỗ Đức Dục",
  "otype" : "person"
} {
  "name" : "Phạm Văn Xảo",
  "otype" : "person"
} {
  "name" : "Nguyễn Văn Tăng",
  "otype" : "person"
} {
  "name" : "Nguyễn Đình Chiểu",
  "otype" : "person"
} {
  "name" : "Mai Anh Đào",
  "otype" : "person"
} {
  "name" : "Đinh Lễ",
  "otype" : "person"
} {
  "name" : "Nguyễn Chánh Sắt",
  "otype" : "person"
} {
  "name" : "Vũ Xuân Thiều",
  "otype" : "person"
} {
  "name" : "Nguyễn Củu Vân",
  "otype" : "person"
} {
  "name" : "Nguyễn Nhữ Lãm",
  "otype" : "person"
} {
  "name" : "Lê Anh Xuân",
  "otype" : "person"
} {
  "name" : "Vũ Tiến",
  "otype" : "person"
} {
  "name" : "Nguyễn Văn Vạn",
  "otype" : "person"
} {
  "name" : "Hồ Nam",
  "otype" : "person"
} {
  "name" : "Phạm Bân",
  "otype" : "person"
} {
  "name" : "Vũ Vân",
  "otype" : "person"
} {
  "name" : "Nguyễn Thái Học",
  "otype" : "person"
} {
  "name" : "Trương Thị Kiện",
  "otype" : "person"
} {
  "name" : "Phan Rang",
  "otype" : "person"
} {
  "name" : "Đinh Lạc",
  "otype" : "person"
} {
  "name" : "Mai Xuân Trưởng",
  "otype" : "person"
} {
  "name" : "Đặng Huy Trứ",
  "otype" : "person"
} {
  "name" : "Đinh Hải",
  "otype" : "person"
} {
  "name" : "Mai Hịch",
  "otype" : "person"
} {
  "name" : "Nguyễn Thiếp",
  "otype" : "person"
} {
  "name" : "Vũ Loan",
  "otype" : "person"
} {
  "name" : "Đinh Tiến",
  "otype" : "person"
} {
  "name" : "Nguyễn Trương Lợi",
  "otype" : "person"
} {
  "name" : "Triệu Ái",
  "otype" : "person"
} {
  "name" : "Bùi Thị Điệt",
  "otype" : "person"
} {
  "name" : "Bùi Hữu Diên",
  "otype" : "person"
} {
  "name" : "Châu Nga",
  "otype" : "person"
} {
  "name" : "Nguyễn Thành Hãn",
  "otype" : "person"
} {
  "name" : "Hoàng Hà",
  "otype" : "person"
} {
  "name" : "Triệu Ẩu",
  "otype" : "person"
} {
  "name" : "Lê Thái Tổ",
  "otype" : "person"
} {
  "name" : "Trương Văn Nga",
  "otype" : "person"
} {
  "name" : "Châu Văn Tiếp",
  "otype" : "person"
} {
  "name" : "Triệu Tài",
  "otype" : "person"
} {
  "name" : "Phan Phú Tiên",
  "otype" : "person"
} {
  "name" : "Nguyễn Việt Dũng",
  "otype" : "person"
} {
  "name" : "Phan Huy Điển",
  "otype" : "person"
} {
  "name" : "Trần Công Hiến",
  "otype" : "person"
} {
  "name" : "Nguyễn Huy Tự",
  "otype" : "person"
} {
  "name" : "Trần Trọng Khiêm",
  "otype" : "person"
} {
  "name" : "Hoàng Tung",
  "otype" : "person"
} {
  "name" : "Trần Thành Ngọ",
  "otype" : "person"
} {
  "name" : "Nguyễn Ngọc Phương",
  "otype" : "person"
} {
  "name" : "Lê Minh",
  "otype" : "person"
} {
  "name" : "Trần Quốc Toản",
  "otype" : "person"
} {
  "name" : "Nguyễn Văn Thạnh",
  "otype" : "person"
} {
  "name" : "Đoàn Thị Liên",
  "otype" : "person"
} {
  "name" : "Châu Ổ",
  "otype" : "person"
} {
  "name" : "Dương Cát Lợi",
  "otype" : "person"
} {
  "name" : "Bùi Văn Bình",
  "otype" : "person"
} {
  "name" : "Đặng Thái Mai",
  "otype" : "person"
} {
  "name" : "Nguyễn Sỹ Sách",
  "otype" : "person"
} {
  "name" : "Đặng Văn Kiều",
  "otype" : "person"
} {
  "name" : "Châu Khê",
  "otype" : "person"
} {
  "name" : "Mai Ninh",
  "otype" : "person"
} {
  "name" : "Lê Trân",
  "otype" : "person"
} {
  "name" : "Hoàng Phan Thái",
  "otype" : "person"
} {
  "name" : "Nguyễn Trãi",
  "otype" : "person"
} {
  "name" : "Dương Văn Nga",
  "otype" : "person"
} {
  "name" : "Phan Thúc Duyên",
  "otype" : "person"
} {
  "name" : "Đoàn Trần Nghiệp",
  "otype" : "person"
} {
  "name" : "Lê Huân",
  "otype" : "person"
} {
  "name" : "Hoàng Hanh",
  "otype" : "person"
} {
  "name" : "Đặng Văn Ngữ",
  "otype" : "person"
} {
  "name" : "Đinh Xá",
  "otype" : "person"
} {
  "name" : "Nguyễn Duy Dương",
  "otype" : "person"
} {
  "name" : "Đặng Sơn",
  "otype" : "person"
} {
  "name" : "Phan Huy Ôn",
  "otype" : "person"
} {
  "name" : "Triệu Thượng",
  "otype" : "person"
} {
  "name" : "Nguyễn Bá Luật",
  "otype" : "person"
} {
  "name" : "Nguyễn Cừu Phú",
  "otype" : "person"
} {
  "name" : "Nguyễn Huy Tưởng",
  "otype" : "person"
} {
  "name" : "Lê Thanh",
  "otype" : "person"
} {
  "name" : "Trần Đình Xu",
  "otype" : "person"
} {
  "name" : "Phạm Văn Khoẻ",
  "otype" : "person"
} {
  "name" : "Nguyễn Hậu",
  "otype" : "person"
} {
  "name" : "Nguyễn Tri Phương",
  "otype" : "person"
} {
  "name" : "Trần Quí Cáp",
  "otype" : "person"
} {
  "name" : "Hoàng Cương",
  "otype" : "person"
} {
  "name" : "Nguyễn Cao Luyện",
  "otype" : "person"
} {
  "name" : "Lê Thị Tạo",
  "otype" : "person"
} {
  "name" : "Mai Hoa Thôn",
  "otype" : "person"
} {
  "name" : "Nguyễn An Khương",
  "otype" : "person"
} {
  "name" : "Phan Đình Phùng",
  "otype" : "person"
} {
  "name" : "Lê Đình Cẩn",
  "otype" : "person"
} {
  "name" : "Trần Tuấn Khải",
  "otype" : "person"
} {
  "name" : "Phan Như Thạch",
  "otype" : "person"
} {
  "name" : "Lê Đại",
  "otype" : "person"
} {
  "name" : "Lê Quý Đôn",
  "otype" : "person"
} {
  "name" : "Nguyễn Khả Trạc",
  "otype" : "person"
} {
  "name" : "Nguyễn Chí Thanh",
  "otype" : "person"
} {
  "name" : "phan rang -tháp chàm",
  "otype" : "person"
} {
  "name" : "Châu Đình",
  "otype" : "person"
} {
  "name" : "Đào Văn Thử",
  "otype" : "person"
} {
  "name" : "Lưu Trọng Lư",
  "otype" : "person"
} {
  "name" : "Nguyễn Phong Sắc",
  "otype" : "person"
} {
  "name" : "Trương Hanh",
  "otype" : "person"
} {
  "name" : "Phan Dăng Lưu",
  "otype" : "person"
} {
  "name" : "Hồ Bá Kiện",
  "otype" : "person"
} {
  "name" : "Vũ Vinh",
  "otype" : "person"
} {
  "name" : "Nguyễn Văn Phú",
  "otype" : "person"
} {
  "name" : "Vũ Hòa",
  "otype" : "person"
} {
  "name" : "Hoàng Nam",
  "otype" : "person"
} {
  "name" : "Bùi Thanh Khiết",
  "otype" : "person"
} {
  "name" : "Lê Thị Xuyến",
  "otype" : "person"
} {
  "name" : "Trần Tấn",
  "otype" : "person"
} {
  "name" : "Nguyễn Trãi Nối Dài",
  "otype" : "person"
} {
  "name" : "Trần Quốc Tuấn",
  "otype" : "person"
} {
  "name" : "Châu Điền",
  "otype" : "person"
} {
  "name" : "Trần Nguyên Đán",
  "otype" : "person"
} {
  "name" : "Nguyễn Đức Trung",
  "otype" : "person"
} {
  "name" : "Hoàng Việt",
  "otype" : "person"
} {
  "name" : "Lý Đạo Thành",
  "otype" : "person"
} {
  "name" : "Trương Minh Giảng",
  "otype" : "person"
} {
  "name" : "Đoàn Phú Tứ",
  "otype" : "person"
} {
  "name" : "Nguyễn Văn Lên",
  "otype" : "person"
} {
  "name" : "Phạm Văn Chí",
  "otype" : "person"
} {
  "name" : "Lê Vĩnh Hòa",
  "otype" : "person"
} {
  "name" : "Đinh Điền",
  "otype" : "person"
} {
  "name" : "Lê Bá Trịnh",
  "otype" : "person"
} {
  "name" : "Phạm Thế Hiển",
  "otype" : "person"
} {
  "name" : "Lê Hồng Phong",
  "otype" : "person"
} {
  "name" : "Vũ Quang",
  "otype" : "person"
} {
  "name" : "Lê Thị Hồng Gấm",
  "otype" : "person"
} {
  "name" : "Dương Đức",
  "otype" : "person"
} {
  "name" : "Lê Sao",
  "otype" : "person"
} {
  "name" : "Triệu Quốc Đạt",
  "otype" : "person"
} {
  "name" : "Nguyễn Côn Trứ",
  "otype" : "person"
} {
  "name" : "Nguyễn Bỉnh Khiêm",
  "otype" : "person"
} {
  "name" : "Nguyễn Cư Trinh",
  "otype" : "person"
} {
  "name" : "Lê Hóa",
  "otype" : "person"
} {
  "name" : "Nguyễn Tư Nghiêm",
  "otype" : "person"
} {
  "name" : "Trần Văn Hoài",
  "otype" : "person"
} {
  "name" : "Lê Văn Lương Kéo Dài",
  "otype" : "person"
} {
  "name" : "Nguyễn Giản Thanh",
  "otype" : "person"
} {
  "name" : "Lê Trì",
  "otype" : "person"
} {
  "name" : "Nguyễn Khắc Viện",
  "otype" : "person"
} {
  "name" : "Nguyễn Văn Chi",
  "otype" : "person"
} {
  "name" : "Phan Xích Long",
  "otype" : "person"
} {
  "name" : "Vũ Oai",
  "otype" : "person"
} {
  "name" : "Hoàng Sĩ Khải",
  "otype" : "person"
} {
  "name" : "Nguyễn Văn Bình",
  "otype" : "person"
} {
  "name" : "Lý Thái Tông",
  "otype" : "person"
} {
  "name" : "Lê Trực",
  "otype" : "person"
} {
  "name" : "Nguyễn Hữu Cảnh",
  "otype" : "person"
} {
  "name" : "Lê Đình Quảng",
  "otype" : "person"
} {
  "name" : "Nguyễn Đỗ Cung",
  "otype" : "person"
} {
  "name" : "Châu Phú",
  "otype" : "person"
} {
  "name" : "Trần Quý Khoách",
  "otype" : "person"
} {
  "name" : "Dương Bá Trạc",
  "otype" : "person"
} {
  "name" : "Hồ Bá Phấn",
  "otype" : "person"
} {
  "name" : "Nguyễn Huệ",
  "otype" : "person"
} {
  "name" : "Nguyễn Văn Siêu",
  "otype" : "person"
} {
  "name" : "Phan Châu Trinh",
  "otype" : "person"
} {
  "name" : "Trần Doãn Khanh",
  "otype" : "person"
} {
  "name" : "Châu Quang",
  "otype" : "person"
} {
  "name" : "Nguyễn Thị Minh",
  "otype" : "person"
} {
  "name" : "Nguyễn Ảnh Thủ",
  "otype" : "person"
} {
  "name" : "Triệu Việt Vương",
  "otype" : "person"
} {
  "name" : "Trương Đình Hội",
  "otype" : "person"
} {
  "name" : "Nguyễn Thành Vĩnh",
  "otype" : "person"
} {
  "name" : "Nguyễn Công Bao",
  "otype" : "person"
} {
  "name" : "Lê Công Kiều",
  "otype" : "person"
} {
  "name" : "Trần Lục",
  "otype" : "person"
} {
  "name" : "Trần Việt Châu",
  "otype" : "person"
} {
  "name" : "Nguyễn Chí Diễu",
  "otype" : "person"
} {
  "name" : "Lê Thiện",
  "otype" : "person"
} {
  "name" : "Lê Tấn Kế",
  "otype" : "person"
} {
  "name" : "Nguyễn Xuân Phụng",
  "otype" : "person"
} {
  "name" : "Châu Bính",
  "otype" : "person"
} {
  "name" : "Lý Tự Trọng",
  "otype" : "person"
} {
  "name" : "Nguyễn Văn Dương",
  "otype" : "person"
} {
  "name" : "Lê Văn Thêm",
  "otype" : "person"
} {
  "name" : "Hoàng Liệt",
  "otype" : "person"
} {
  "name" : "Nguyễn Ngọc Nại",
  "otype" : "person"
} {
  "name" : "Nguyễn Du",
  "otype" : "person"
} {
  "name" : "Phạm Đăng Giảng",
  "otype" : "person"
} {
  "name" : "Phạm Tuấn Tài",
  "otype" : "person"
} {
  "name" : "Trịnh Đình Trọng",
  "otype" : "person"
} {
  "name" : "Nguyễn Án",
  "otype" : "person"
} {
  "name" : "Hoàng Thắng",
  "otype" : "person"
} {
  "name" : "Trần Phán",
  "otype" : "person"
} {
  "name" : "Vũ Muộn",
  "otype" : "person"
} {
  "name" : "Phạm Văn Đồng",
  "otype" : "person"
} {
  "name" : "Trần Văn Chuông",
  "otype" : "person"
} {
  "name" : "Hoàng Thị Loan",
  "otype" : "person"
} {
  "name" : "Lê Chính Đáng",
  "otype" : "person"
} {
  "name" : "Nguyễn Thái Bình",
  "otype" : "person"
} {
  "name" : "Đinh Liệt",
  "otype" : "person"
} {
  "name" : "Phan Bội Châu",
  "otype" : "person"
} {
  "name" : "Đỗ Trọng Trí",
  "otype" : "person"
} {
  "name" : "Trần Nhân Tôn",
  "otype" : "person"
} {
  "name" : "Nguyễn Bá Phát",
  "otype" : "person"
} {
  "name" : "Mai",
  "otype" : "person"
} {
  "name" : "Nguyễn Đình Chi",
  "otype" : "person"
} {
  "name" : "Nguyễn Sinh Sắc",
  "otype" : "person"
} {
  "name" : "Phan Văn Năm",
  "otype" : "person"
} {
  "name" : "Lê Phụng Hiểu",
  "otype" : "person"
} {
  "name" : "Đoàn Văn Bơ",
  "otype" : "person"
} {
  "name" : "Phạm Viết Chánh",
  "otype" : "person"
} {
  "name" : "Phạm Cự Lượng",
  "otype" : "person"
} {
  "name" : "Lê Trọng Mân",
  "otype" : "person"
} {
  "name" : "Lê Thước",
  "otype" : "person"
} {
  "name" : "Lê Thiệt",
  "otype" : "person"
} {
  "name" : "Hồ",
  "otype" : "person"
} {
  "name" : "Lê Tân Bê",
  "otype" : "person"
} {
  "name" : "Lê Văn Quới",
  "otype" : "person"
} {
  "name" : "Phan Khiêm Ích",
  "otype" : "person"
} {
  "name" : "Trần Thế Xương",
  "otype" : "person"
} {
  "name" : "Đặng Đại Độ",
  "otype" : "person"
} {
  "name" : "Trần Văn Quang",
  "otype" : "person"
} {
  "name" : "Phan Văn Chương",
  "otype" : "person"
} {
  "name" : "Châu Cường",
  "otype" : "person"
} {
  "name" : "Nguyễn Quang Bích",
  "otype" : "person"
} {
  "name" : "Nguyễn Lộ Trạch",
  "otype" : "person"
} {
  "name" : "Châu Pha",
  "otype" : "person"
} {
  "name" : "Lê Quang Sung",
  "otype" : "person"
} {
  "name" : "Lưu Xuân Tín",
  "otype" : "person"
} {
  "name" : "Vũ Trọng Phụng",
  "otype" : "person"
} {
  "name" : "Hồ Đắc Di",
  "otype" : "person"
} {
  "name" : "Lê Bình",
  "otype" : "person"
} {
  "name" : "Hoàng Sa",
  "otype" : "person"
} {
  "name" : "Lý Văn Tổ",
  "otype" : "person"
} {
  "name" : "Đinh Trang Hòa",
  "otype" : "person"
} {
  "name" : "Châu Lộc",
  "otype" : "person"
} {
  "name" : "Trần Xuân Soạn",
  "otype" : "person"
} {
  "name" : "Đặng Cương",
  "otype" : "person"
} {
  "name" : "Nguyễn Việt Hồng",
  "otype" : "person"
} {
  "name" : "Nguyễn Hữu Tiến",
  "otype" : "person"
} {
  "name" : "Đinh Bình",
  "otype" : "person"
} {
  "name" : "Trần Ngọc Quế",
  "otype" : "person"
} {
  "name" : "Hồ Ngọc Lãm",
  "otype" : "person"
} {
  "name" : "Đoàn Đào",
  "otype" : "person"
} {
  "name" : "Hoàng Xuân Nhị",
  "otype" : "person"
} {
  "name" : "Đặng Minh Khiêm",
  "otype" : "person"
} {
  "name" : "Nguyễn Hữu Thọ",
  "otype" : "person"
} {
  "name" : "Châu Hội",
  "otype" : "person"
} {
  "name" : "Đỗ Tấn Phong",
  "otype" : "person"
} {
  "name" : "Nguyễn Cửu Phú",
  "otype" : "person"
} {
  "name" : "Vũ Chấn",
  "otype" : "person"
} {
  "name" : "Châu Vĩnh Tế",
  "otype" : "person"
} {
  "name" : "Lê Khôi",
  "otype" : "person"
} {
  "name" : "Nguyễn Thanh Tuyền",
  "otype" : "person"
} {
  "name" : "Nguyễn Trọng Tuyền",
  "otype" : "person"
} {
  "name" : "Hồ Sơn",
  "otype" : "person"
} {
  "name" : "Trần Trọng Cung",
  "otype" : "person"
} {
  "name" : "Trần Xuân Hòa",
  "otype" : "person"
} {
  "name" : "Nguyễn Xuân Ôn",
  "otype" : "person"
} {
  "name" : "Trần Thúc Nhân",
  "otype" : "person"
} {
  "name" : "Lê Văn Tám",
  "otype" : "person"
} {
  "name" : "Dương Thành",
  "otype" : "person"
} {
  "name" : "Nguyễn Văn Bá",
  "otype" : "person"
} {
  "name" : "Nguyễn Việt Khái",
  "otype" : "person"
} {
  "name" : "Bùi Dương Lịch",
  "otype" : "person"
} {
  "name" : "Phan Trọng Tuệ",
  "otype" : "person"
} {
  "name" : "Trần Thủ Độ",
  "otype" : "person"
} {
  "name" : "Nguyễn Công Trứ",
  "otype" : "person"
} {
  "name" : "Phạm Ngọc",
  "otype" : "person"
} {
  "name" : "Nguyễn Thị Triệu",
  "otype" : "person"
} {
  "name" : "Hoàng Phúc",
  "otype" : "person"
} {
  "name" : "Đào Hữu Cảnh",
  "otype" : "person"
} {
  "name" : "Lý Long Tường",
  "otype" : "person"
} {
  "name" : "Bùi Cẩm Hồ",
  "otype" : "person"
} {
  "name" : "Đinh Văn",
  "otype" : "person"
} {
  "name" : "Hoàng Động",
  "otype" : "person"
} {
  "name" : "Lê Lợi",
  "otype" : "person"
} {
  "name" : "Nguyễn Nhược Thi",
  "otype" : "person"
} {
  "name" : "Nguyễn Trãi Cũ",
  "otype" : "person"
} {
  "name" : "Hoàng Đan",
  "otype" : "person"
} {
  "name" : "Châu Hồng",
  "otype" : "person"
} {
  "name" : "Đoàn Hữu Trưng",
  "otype" : "person"
} {
  "name" : "Nguyễn Phúc Nguyên",
  "otype" : "person"
} {
  "name" : "Trần Quý",
  "otype" : "person"
} {
  "name" : "Nguyễn Đình Kiên",
  "otype" : "person"
} {
  "name" : "Hoàng Diệu",
  "otype" : "person"
} {
  "name" : "Phan Phù Tiên",
  "otype" : "person"
} {
  "name" : "Hoàng Châu",
  "otype" : "person"
} {
  "name" : "Phan Sơn",
  "otype" : "person"
} {
  "name" : "Lưu Kỳ",
  "otype" : "person"
} {
  "name" : "Đoàn Công Bửu",
  "otype" : "person"
} {
  "name" : "Phan Huy",
  "otype" : "person"
} {
  "name" : "Trần Thị Nghĩ",
  "otype" : "person"
} {
  "name" : "Nguyễn Cừ",
  "otype" : "person"
} {
  "name" : "Đỗ Văn Sửu",
  "otype" : "person"
} {
  "name" : "Trần Quang Khải",
  "otype" : "person"
} {
  "name" : "Lê Chung",
  "otype" : "person"
} {
  "name" : "Nguyễn Hoàng",
  "otype" : "person"
} {
  "name" : "Triệu Độ",
  "otype" : "person"
} {
  "name" : "Nguyễn Trọng Tuyển",
  "otype" : "person"
} {
  "name" : "Nguyễn Sinh Cung",
  "otype" : "person"
} {
  "name" : "Nguyễn Văn Tráng",
  "otype" : "person"
} {
  "name" : "Dương Khuê",
  "otype" : "person"
} {
  "name" : "Lê Viết Lượng",
  "otype" : "person"
} {
  "name" : "Đinh Thành",
  "otype" : "person"
} {
  "name" : "Lê Văn Việt",
  "otype" : "person"
} {
  "name" : "Lê Văn Huân",
  "otype" : "person"
} {
  "name" : "Vũ Ninh",
  "otype" : "person"
} {
  "name" : "Lê Cao Lãng",
  "otype" : "person"
} {
  "name" : "Nguyễn Phi Khanh",
  "otype" : "person"
} {
  "name" : "Lê Cao Lãnh",
  "otype" : "person"
} {
  "name" : "Nguyễn Dữ",
  "otype" : "person"
} {
  "name" : "Nguyễn Văn Luông",
  "otype" : "person"
} {
  "name" : "Đỗ Hữu Vị",
  "otype" : "person"
} {
  "name" : "Trương Định",
  "otype" : "person"
} {
  "name" : "Châu Can",
  "otype" : "person"
} {
  "name" : "Trần Cung",
  "otype" : "person"
} {
  "name" : "hồ thị kỉ",
  "otype" : "person"
} {
  "name" : "Phạm Hữu Chí",
  "otype" : "person"
} {
  "name" : "Triệu Đề",
  "otype" : "person"
} {
  "name" : "Đoàn Văn Tiến",
  "otype" : "person"
} {
  "name" : "Phạm Văn Bạch",
  "otype" : "person"
} {
  "name" : "Châu Hòa",
  "otype" : "person"
} {
  "name" : "Lý Công Uẩn",
  "otype" : "person"
} {
  "name" : "Lê Lai",
  "otype" : "person"
} {
  "name" : "Lý Học",
  "otype" : "person"
} {
  "name" : "Nguyễn Văn Bứa",
  "otype" : "person"
} {
  "name" : "Trần Tế Xương",
  "otype" : "person"
} {
  "name" : "Lê Thị Hoạnh",
  "otype" : "person"
} {
  "name" : "Dương Minh Châu",
  "otype" : "person"
} {
  "name" : "Bùi Minh Trực",
  "otype" : "person"
} {
  "name" : "Đoàn Tùng",
  "otype" : "person"
} {
  "name" : "Lê Văn Linh",
  "otype" : "person"
} {
  "name" : "Nguyễn Khoa Chiêm",
  "otype" : "person"
} {
  "name" : "Đỗ Hành",
  "otype" : "person"
} {
  "name" : "Châu Bình",
  "otype" : "person"
} {
  "name" : "Lê Ngọc Hân",
  "otype" : "person"
} {
  "name" : "Phan Đinhg Giót",
  "otype" : "person"
} {
  "name" : "Hoàng Xá",
  "otype" : "person"
} {
  "name" : "Dương Nội",
  "otype" : "person"
} {
  "name" : "Hoàng Đồng",
  "otype" : "person"
} {
  "name" : "Trần Văn Khéo",
  "otype" : "person"
} {
  "name" : "Trần Huy Liệu",
  "otype" : "person"
} {
  "name" : "Nguyễn Oanh",
  "otype" : "person"
} {
  "name" : "Nguyễn An Ninh",
  "otype" : "person"
} {
  "name" : "Phan Văn Trị",
  "otype" : "person"
} {
  "name" : "Vũ Duy Linh",
  "otype" : "person"
} {
  "name" : "Trần Đoàn Khánh",
  "otype" : "person"
} {
  "name" : "Nguyễn Văn Đậu",
  "otype" : "person"
} {
  "name" : "Lưu Quang Vũ",
  "otype" : "person"
} {
  "name" : "Nguyễn Hàm Ninh",
  "otype" : "person"
} {
  "name" : "Triệu Thuận",
  "otype" : "person"
} {
  "name" : "Hoàng Đông",
  "otype" : "person"
} {
  "name" : "Nguyễn Văn Bi",
  "otype" : "person"
} {
  "name" : "Lê Văn Thiêm",
  "otype" : "person"
} {
  "name" : "Lê Quốc Hưng",
  "otype" : "person"
} {
  "name" : "Nguyễn Trong Trí",
  "otype" : "person"
} {
  "name" : "Đinh Hưng",
  "otype" : "person"
} {
  "name" : "Đào Dương",
  "otype" : "person"
} {
  "name" : "Nguyễn Văn Mạnh",
  "otype" : "person"
} {
  "name" : "Nguyễn Cảnh Chân",
  "otype" : "person"
} {
  "name" : "Dương Tự Quán",
  "otype" : "person"
} {
  "name" : "Lê Sát",
  "otype" : "person"
} {
  "name" : "Đỗ Động",
  "otype" : "person"
} {
  "name" : "Nguyễn Khắc Nhu",
  "otype" : "person"
} {
  "name" : "Phan Chu Trinh",
  "otype" : "person"
} {
  "name" : "Triệu Long",
  "otype" : "person"
} {
  "name" : "Hồ Văn Long",
  "otype" : "person"
} {
  "name" : "Nguyễn Úy",
  "otype" : "person"
} {
  "name" : "Lê Tấn Quốc",
  "otype" : "person"
} {
  "name" : "Lê Ngọc Hân",
  "otype" : "person"
} {
  "name" : "Lê Đình Tám",
  "otype" : "person"
} {
  "name" : "Hồ Thị Kỷ",
  "otype" : "person"
} {
  "name" : "Nguyễn Thiện Kế",
  "otype" : "person"
} {
  "name" : "Trương Văn Hoàn",
  "otype" : "person"
} {
  "name" : "Hoàng Hoa",
  "otype" : "person"
} {
  "name" : "Phạm Hữu Lầu",
  "otype" : "person"
} {
  "name" : "Lê Văn Khói",
  "otype" : "person"
} {
  "name" : "Phan Sào Nam",
  "otype" : "person"
} {
  "name" : "Vũ  Quỳnh",
  "otype" : "person"
} {
  "name" : "Vũ Bình",
  "otype" : "person"
} {
  "name" : "Phan Cát Tựu",
  "otype" : "person"
} {
  "name" : "Nguyễn Hữu Thoại",
  "otype" : "person"
} {
  "name" : "Trần Hữu Tước",
  "otype" : "person"
} {
  "name" : "Phan",
  "otype" : "person"
} {
  "name" : "Mai Động",
  "otype" : "person"
} {
  "name" : "Nguyễn Minh Hoàng",
  "otype" : "person"
} {
  "name" : "Nguyễn Cao",
  "otype" : "person"
} {
  "name" : "Nguyễn Tử Lục",
  "otype" : "person"
} {
  "name" : "Hoàng Mai",
  "otype" : "person"
} {
  "name" : "Lê Văn Duyệt",
  "otype" : "person"
} {
  "name" : "Nguyễn Hới",
  "otype" : "person"
} {
  "name" : "Trần Trọng Kim",
  "otype" : "person"
} {
  "name" : "Nguyễn Văng Tráng",
  "otype" : "person"
} {
  "name" : "Lưu Nghiệp Anh",
  "otype" : "person"
} {
  "name" : "Châu Quế Thượng",
  "otype" : "person"
} {
  "name" : "Đoàn Giỏi",
  "otype" : "person"
} {
  "name" : "Triệu Lộc",
  "otype" : "person"
} {
  "name" : "Đoàn Nhữ Hải",
  "otype" : "person"
} {
  "name" : "Lê Văn Lương",
  "otype" : "person"
} {
  "name" : "Phạm Thiều",
  "otype" : "person"
} {
  "name" : "Hồ Thầu",
  "otype" : "person"
} {
  "name" : "Lê Ngung",
  "otype" : "person"
} {
  "name" : "Lê Trung Nghĩa",
  "otype" : "person"
} {
  "name" : "Lê Phát Đạt",
  "otype" : "person"
} {
  "name" : "Hoàng Tây",
  "otype" : "person"
} {
  "name" : "Hoàng Tân",
  "otype" : "person"
} {
  "name" : "Hoàng Ninh",
  "otype" : "person"
} {
  "name" : "Nguyễn Văn Ni",
  "otype" : "person"
} {
  "name" : "Lê Văn Sĩ",
  "otype" : "person"
} {
  "name" : "Nguyễn Phạm Tuân",
  "otype" : "person"
} {
  "name" : "Vũ Chí Thắng",
  "otype" : "person"
} {
  "name" : "Trần Quang Quờn",
  "otype" : "person"
} {
  "name" : "Trịnh Đình Thảo",
  "otype" : "person"
} {
  "name" : "Đỗ Công Tường",
  "otype" : "person"
} {
  "name" : "Đặng Tiến Đông",
  "otype" : "person"
} {
  "name" : "Nguyễn Thức Đường",
  "otype" : "person"
} {
  "name" : "Lý Tế Xuyên",
  "otype" : "person"
} {
  "name" : "Nguyễn Văn Cư",
  "otype" : "person"
} {
  "name" : "Lý Nhân",
  "otype" : "person"
} {
  "name" : "Nguyễn Lý",
  "otype" : "person"
} {
  "name" : "Châu Kim",
  "otype" : "person"
} {
  "name" : "Đỗ Thừa Tự",
  "otype" : "person"
} {
  "name" : "Phan Văn Trường",
  "otype" : "person"
} {
  "name" : "Nguyễn Sĩ Sách",
  "otype" : "person"
} {
  "name" : "Trần Phú Cương",
  "otype" : "person"
} {
  "name" : "Lê Lâm",
  "otype" : "person"
} {
  "name" : "Phan Hiệp",
  "otype" : "person"
} {
  "name" : "Hồ Văn Huê",
  "otype" : "person"
} {
  "name" : "đặng xá",
  "otype" : "person"
} {
  "name" : "Châu Thuận",
  "otype" : "person"
} {
  "name" : "Nguyễn Duy Hiếu",
  "otype" : "person"
} {
  "name" : "Lê Công Phép",
  "otype" : "person"
} {
  "name" : "Nguyễn Văn Thân",
  "otype" : "person"
} {
  "name" : "trần can",
  "otype" : "person"
} {
  "name" : "Đào Duy Anh",
  "otype" : "person"
} {
  "name" : "Đinh Tân",
  "otype" : "person"
} {
  "name" : "Đỗ Thành Nhân",
  "otype" : "person"
} {
  "name" : "Lý Bôn",
  "otype" : "person"
} {
  "name" : "Nguyễn Phúc",
  "otype" : "person"
} {
  "name" : "Phạm Văn Sáng",
  "otype" : "person"
} {
  "name" : "Bùi Văn Ngữ",
  "otype" : "person"
} {
  "name" : "Nguyễn Hồng Đào",
  "otype" : "person"
} {
  "name" : "Nguyễn Văn Tạo",
  "otype" : "person"
} {
  "name" : "Nguyễn Bình",
  "otype" : "person"
} {
  "name" : "Hồ Chí Minh",
  "otype" : "person"
} {
  "name" : "Đào Nguyên Phổ",
  "otype" : "person"
} {
  "name" : "Hoàng Quốc Việt",
  "otype" : "person"
} {
  "name" : "Phan Đình Hổ",
  "otype" : "person"
} {
  "name" : "Dương Xuân Hội",
  "otype" : "person"
} {
  "name" : "Nguyễn Trác Luân",
  "otype" : "person"
} {
  "name" : "Đào Trinh Nhất",
  "otype" : "person"
} {
  "name" : "Nguyễn Văn Giai",
  "otype" : "person"
} {
  "name" : "Trịnh Khắc Lập",
  "otype" : "person"
} {
  "name" : "Trương Đình Trọng",
  "otype" : "person"
} {
  "name" : "Hoàng Ngọc Phách",
  "otype" : "person"
} {
  "name" : "Nguyễn Văn Gia",
  "otype" : "person"
} {
  "name" : "Đỗ Quang",
  "otype" : "person"
} {
  "name" : "Nguyễn Cao Nam",
  "otype" : "person"
} {
  "name" : "Trần Khắc Chân",
  "otype" : "person"
} {
  "name" : "Đỗ Bí",
  "otype" : "person"
} {
  "name" : "Phạm Huy Thông",
  "otype" : "person"
} {
  "name" : "Phan Đăng Giảng",
  "otype" : "person"
} {
  "name" : "Đỗ Thế Duyên",
  "otype" : "person"
} {
  "name" : "Trương Văn Đa",
  "otype" : "person"
} {
  "name" : "Bùi Xuân Trạch",
  "otype" : "person"
} {
  "name" : "Hồ Tùng Mậu",
  "otype" : "person"
} {
  "name" : "Nguyễn Thành Ý",
  "otype" : "person"
} {
  "name" : "Nguyễn Giao",
  "otype" : "person"
} {
  "name" : "Nguyễn Ngọc Cung",
  "otype" : "person"
} {
  "name" : "Phan Bá Phiến",
  "otype" : "person"
} {
  "name" : "Vũ Phúc",
  "otype" : "person"
} {
  "name" : "Lê Văn Sỹ",
  "otype" : "person"
} {
  "name" : "Vũ Yến",
  "otype" : "person"
} {
  "name" : "Châu Đốc",
  "otype" : "person"
} {
  "name" : "Trần Bình Trọng",
  "otype" : "person"
} {
  "name" : "Mai Thúc Loan",
  "otype" : "person"
} {
  "name" : "Lê Quốc Trinh",
  "otype" : "person"
} {
  "name" : "Đặng Xá",
  "otype" : "person"
} {
  "name" : "Trần Quốc Thảo",
  "otype" : "person"
} {
  "name" : "Mai Đông",
  "otype" : "person"
} {
  "name" : "Triệu Thị Trinh",
  "otype" : "person"
} {
  "name" : "Lê Hoàng Phái",
  "otype" : "person"
} {
  "name" : "Lê Thị Hà",
  "otype" : "person"
} {
  "name" : "Dương Bá Cung",
  "otype" : "person"
} {
  "name" : "Lê Lư",
  "otype" : "person"
} {
  "name" : "Bùi Xương Trạch",
  "otype" : "person"
} {
  "name" : "Đoàn Hữu Trung",
  "otype" : "person"
} {
  "name" : "Nguyễn Văn Trường",
  "otype" : "person"
} {
  "name" : "Triệu Nữ Vương",
  "otype" : "person"
} {
  "name" : "Nguyễn Tiểu La",
  "otype" : "person"
} {
  "name" : "Lê Văn Miến",
  "otype" : "person"
} {
  "name" : "Nguyễn Minh Châu",
  "otype" : "person"
} {
  "name" : "Bùi Quốc Khái",
  "otype" : "person"
} {
  "name" : "Lê Thạch",
  "otype" : "person"
} {
  "name" : "Nguyễn Văn Trổi",
  "otype" : "person"
} {
  "name" : "Châu Hóa",
  "otype" : "person"
} {
  "name" : "Lý Thái Tổ",
  "otype" : "person"
} {
  "name" : "Trần Ngọc Diện",
  "otype" : "person"
} {
  "name" : "Nguyễn Tư Giản",
  "otype" : "person"
} {
  "name" : "Nguyễn Thị Nhỏ",
  "otype" : "person"
} {
  "name" : "phan rang",
  "otype" : "person"
} {
  "name" : "Trần Văn Khánh",
  "otype" : "person"
} {
  "name" : "Trương Văn Lĩnh",
  "otype" : "person"
} {
  "name" : "Lê Hồng",
  "otype" : "person"
} {
  "name" : "Nguyễn Trực",
  "otype" : "person"
} {
  "name" : "Đặng Trần Côn",
  "otype" : "person"
} {
  "name" : "Mai Pha",
  "otype" : "person"
} {
  "name" : "Lê Tuấn Mậu",
  "otype" : "person"
} {
  "name" : "Dương Văn Hạnh",
  "otype" : "person"
} {
  "name" : "Mai Dịch",
  "otype" : "person"
} {
  "name" : "Trịnh Xá",
  "otype" : "person"
} {
  "name" : "Hoàng Phụ",
  "otype" : "person"
} {
  "name" : "Phạm Hùng",
  "otype" : "person"
} {
  "name" : "Trần Quang Đạo",
  "otype" : "person"
} {
  "name" : "Phạm Ngũ Lão",
  "otype" : "person"
} {
  "name" : "Dương Thủy",
  "otype" : "person"
} {
  "name" : "Lê Ngã",
  "otype" : "person"
} {
  "name" : "Mai Lão Bạng",
  "otype" : "person"
} {
  "name" : "Châu Phú B",
  "otype" : "person"
} {
  "name" : "Nguyễn Văn Dung",
  "otype" : "person"
} {
  "name" : "Châu Phú A",
  "otype" : "person"
} {
  "name" : "Nguyễn Duy",
  "otype" : "person"
} {
  "name" : "Trần Tử Bình",
  "otype" : "person"
} {
  "name" : "Lê Quang Chiểu",
  "otype" : "person"
} {
  "name" : "Đinh Bộ Lĩnh",
  "otype" : "person"
} {
  "name" : "Đặng Quốc Chính",
  "otype" : "person"
} {
  "name" : "Nguyễn Thiệp",
  "otype" : "person"
} {
  "name" : "Trần Não",
  "otype" : "person"
} {
  "name" : "Đoàn Nhữ Hài",
  "otype" : "person"
} {
  "name" : "Phan Điền",
  "otype" : "person"
} {
  "name" : "Trần Khánh Dư",
  "otype" : "person"
} {
  "name" : "Phan Văn Đạt",
  "otype" : "person"
} {
  "name" : "Lê Đình Quản",
  "otype" : "person"
} {
  "name" : "Lê Đình Dương",
  "otype" : "person"
} {
  "name" : "Đặng Đức Thuật",
  "otype" : "person"
} {
  "name" : "Hồ Xá",
  "otype" : "person"
} {
  "name" : "Nguyễn Văn Trỗi",
  "otype" : "person"
} {
  "name" : "Bùi Viện",
  "otype" : "person"
} {
  "name" : "Nguyễn Công Hoan",
  "otype" : "person"
} {
  "name" : "Dương Quang",
  "otype" : "person"
} {
  "name" : "Trương Đăng Quế",
  "otype" : "person"
} {
  "name" : "Phạm Trấn",
  "otype" : "person"
} {
  "name" : "Lưu Quý Kỳ",
  "otype" : "person"
} {
  "name" : "Nguyễn Văn Thành",
  "otype" : "person"
} {
  "name" : "Mai Lão Bang",
  "otype" : "person"
} {
  "name" : "Nguyễn Văn Long",
  "otype" : "person"
} {
  "name" : "Triệu Trung",
  "otype" : "person"
} {
  "name" : "Dương Đông",
  "otype" : "person"
} {
  "name" : "Mai Lâm",
  "otype" : "person"
} {
  "name" : "Vũ Linh",
  "otype" : "person"
} {
  "name" : "Nguyễn Văn Lạc",
  "otype" : "person"
} {
  "name" : "Nguyễn Biểu",
  "otype" : "person"
} {
  "name" : "Nguyễn Văn Quá",
  "otype" : "person"
} {
  "name" : "Nguyễn Hữu Thân",
  "otype" : "person"
} {
  "name" : "Hoàng Kim",
  "otype" : "person"
} {
  "name" : "Mai Bá Hương",
  "otype" : "person"
} {
  "name" : "Nguyễn Trung Nguyệt",
  "otype" : "person"
} {
  "name" : "Phạm Sư Mệnh",
  "otype" : "person"
} {
  "name" : "Bùi Công Trừng",
  "otype" : "person"
} {
  "name" : "Nguyễn Quý Tân",
  "otype" : "person"
} {
  "name" : "Nguyễn Thành Y",
  "otype" : "person"
} {
  "name" : "Nguyễn Cửu Đàm",
  "otype" : "person"
} {
  "name" : "Lý Sơn",
  "otype" : "person"
} {
  "name" : "Nguyễn Tuyển",
  "otype" : "person"
} {
  "name" : "Nguyễn Kim Cương",
  "otype" : "person"
} {
  "name" : "Nguyễn Sơn",
  "otype" : "person"
} {
  "name" : "Hoàng Tích Trí",
  "otype" : "person"
} {
  "name" : "Phan Đăng Lưu",
  "otype" : "person"
} {
  "name" : "Lê Tung",
  "otype" : "person"
}